{
"type": "FeatureCollection",
"name": "nyc-treatmentplant-wgs84",
"crs": { "type": "name", "properties": { "name": "urn:ogc:def:crs:OGC:1.3:CRS84" } },
"features": [
{ "type": "Feature", "properties": { "gid": 1, "drainage_a": 12947, "dry_weathe": "120", "treatment_plant": "OWLS HEAD", "wpcp": "OH", "population": "800,000", "demand": "64" }, "geometry": { "type": "Point", "coordinates": [ -74.03458099, 40.64181365 ] } },
{ "type": "Feature", "properties": { "gid": 2, "drainage_a": 3200, "dry_weathe": "60", "treatment_plant": "RED HOOK", "wpcp": "RH", "population": "200,000", "demand": "16" }, "geometry": { "type": "Point", "coordinates": [ -73.97848587, 40.70227572 ] } },
{ "type": "Feature", "properties": { "gid": 3, "drainage_a": 15087, "dry_weathe": "110", "treatment_plant": "CONEY ISLAND", "wpcp": "CI", "population": "600,000", "demand": "48" }, "geometry": { "type": "Point", "coordinates": [ -73.9335755, 40.59022579 ] } },
{ "type": "Feature", "properties": { "gid": 4, "drainage_a": 10779, "dry_weathe": "40", "treatment_plant": "OAKWOOD BEACH", "wpcp": "OB", "population": "250,000", "demand": "20" }, "geometry": { "type": "Point", "coordinates": [ -74.11880295, 40.55088182 ] } },
{ "type": "Feature", "properties": { "gid": 5, "drainage_a": 0, "dry_weathe": null, "treatment_plant": "SPRING CREEK AUXILIARY PLANT", "wpcp": null, "population": null, "demand": null }, "geometry": { "type": "Point", "coordinates": [ -73.86380281, 40.65880053 ] } },
{ "type": "Feature", "properties": { "gid": 6, "drainage_a": 9665, "dry_weathe": "60", "treatment_plant": "PORT RICHMOND", "wpcp": "PR", "population": "200,000", "demand": "16" }, "geometry": { "type": "Point", "coordinates": [ -74.12547456, 40.63973534 ] } },
{ "type": "Feature", "properties": { "gid": 7, "drainage_a": 6030, "dry_weathe": "170", "treatment_plant": "NORTH RIVER", "wpcp": "NR", "population": "600,000", "demand": "48" }, "geometry": { "type": "Point", "coordinates": [ -73.95608273, 40.82714321 ] } },
{ "type": "Feature", "properties": { "gid": 8, "drainage_a": 12056, "dry_weathe": "275", "treatment_plant": "WARDS ISLAND", "wpcp": "WI", "population": "1,100,000", "demand": "88" }, "geometry": { "type": "Point", "coordinates": [ -73.92395843, 40.78672339 ] } },
{ "type": "Feature", "properties": { "gid": 9, "drainage_a": 16664, "dry_weathe": "200", "treatment_plant": "HUNTS POINT", "wpcp": "HP", "population": "700,000", "demand": "56" }, "geometry": { "type": "Point", "coordinates": [ -73.8831403, 40.80299116 ] } },
{ "type": "Feature", "properties": { "gid": 10, "drainage_a": 6259, "dry_weathe": "45", "treatment_plant": "ROCKAWAY", "wpcp": "ROC", "population": "100,000", "demand": "8" }, "geometry": { "type": "Point", "coordinates": [ -73.82952868, 40.58347051 ] } },
{ "type": "Feature", "properties": { "gid": 11, "drainage_a": 15203, "dry_weathe": "150", "treatment_plant": "BOWERY BAY", "wpcp": "BB", "population": "850,000", "demand": "68" }, "geometry": { "type": "Point", "coordinates": [ -73.89433181, 40.77977337 ] } },
{ "type": "Feature", "properties": { "gid": 12, "drainage_a": 16860, "dry_weathe": "80", "treatment_plant": "TALLMAN ISLAND", "wpcp": "TI", "population": "450,000", "demand": "36" }, "geometry": { "type": "Point", "coordinates": [ -73.83877814, 40.79588524 ] } },
{ "type": "Feature", "properties": { "gid": 13, "drainage_a": 25313, "dry_weathe": "100", "treatment_plant": "JAMAICA", "wpcp": "JAM", "population": "750,000", "demand": "60" }, "geometry": { "type": "Point", "coordinates": [ -73.80840757, 40.66239852 ] } },
{ "type": "Feature", "properties": { "gid": 14, "drainage_a": 15656, "dry_weathe": "310", "treatment_plant": "NEWTOWN CREEK", "wpcp": "NC", "population": "1,100,000", "demand": "88" }, "geometry": { "type": "Point", "coordinates": [ -73.94649942, 40.73265789 ] } },
{ "type": "Feature", "properties": { "gid": 15, "drainage_a": 5907, "dry_weathe": "85", "treatment_plant": "26th WARD", "wpcp": "26W", "population": "300,000", "demand": "24" }, "geometry": { "type": "Point", "coordinates": [ -73.87930189, 40.6518505 ] } }
]
}
